{"doc-10.7": {"Activity": {"true-positive": 1, "false-positive": 7, "true-negative": 0, "false-negative": 7, "precision": 0.125, "recall": 0.125, "f1-score": 0.125, "supports": 8}, "Activity Data": {"true-positive": 2, "false-positive": 6, "true-negative": 0, "false-negative": 6, "precision": 0.25, "recall": 0.25, "f1-score": 0.25, "supports": 8}, "Actor": {"true-positive": 0, "false-positive": 0, "true-negative": 0, "false-negative": 12, "precision": 0.0, "recall": 0.0, "f1-score": 0.0, "supports": 12}, "Further Specification": {"true-positive": 0, "false-positive": 0, "true-negative": 0, "false-negative": 0, "precision": 0.0, "recall": 0.0, "f1-score": 0.0, "supports": 0}, "XOR Gateway": {"true-positive": 0, "false-positive": 0, "true-negative": 0, "false-negative": 1, "precision": 0.0, "recall": 0.0, "f1-score": 0.0, "supports": 1}, "AND Gateway": {"true-positive": 0, "false-positive": 0, "true-negative": 0, "false-negative": 0, "precision": 0.0, "recall": 0.0, "f1-score": 0.0, "supports": 0}, "Condition Specification": {"true-positive": 0, "false-positive": 0, "true-negative": 0, "false-negative": 0, "precision": 0.0, "recall": 0.0, "f1-score": 0.0, "supports": 0}}, "doc-2.2": {"Activity": {"true-positive": 5, "false-positive": 46, "true-negative": 0, "false-negative": 26, "precision": 0.09803921568627451, "recall": 0.16129032258064516, "f1-score": 0.1219512195121951, "supports": 31}, "Activity Data": {"true-positive": 8, "false-positive": 47, "true-negative": 0, "false-negative": 19, "precision": 0.14545454545454545, "recall": 0.2962962962962963, "f1-score": 0.19512195121951217, "supports": 27}, "Actor": {"true-positive": 0, "false-positive": 0, "true-negative": 0, "false-negative": 23, "precision": 0.0, "recall": 0.0, "f1-score": 0.0, "supports": 23}, "Further Specification": {"true-positive": 0, "false-positive": 0, "true-negative": 0, "false-negative": 3, "precision": 0.0, "recall": 0.0, "f1-score": 0.0, "supports": 3}, "XOR Gateway": {"true-positive": 0, "false-positive": 0, "true-negative": 0, "false-negative": 8, "precision": 0.0, "recall": 0.0, "f1-score": 0.0, "supports": 8}, "AND Gateway": {"true-positive": 0, "false-positive": 0, "true-negative": 0, "false-negative": 1, "precision": 0.0, "recall": 0.0, "f1-score": 0.0, "supports": 1}, "Condition Specification": {"true-positive": 0, "false-positive": 0, "true-negative": 0, "false-negative": 6, "precision": 0.0, "recall": 0.0, "f1-score": 0.0, "supports": 6}}, "doc-1.1": {"Activity": {"true-positive": 2, "false-positive": 15, "true-negative": 0, "false-negative": 9, "precision": 0.11764705882352941, "recall": 0.18181818181818182, "f1-score": 0.14285714285714285, "supports": 11}, "Activity Data": {"true-positive": 4, "false-positive": 14, "true-negative": 0, "false-negative": 5, "precision": 0.2222222222222222, "recall": 0.4444444444444444, "f1-score": 0.2962962962962963, "supports": 9}, "Actor": {"true-positive": 0, "false-positive": 0, "true-negative": 0, "false-negative": 8, "precision": 0.0, "recall": 0.0, "f1-score": 0.0, "supports": 8}, "Further Specification": {"true-positive": 0, "false-positive": 0, "true-negative": 0, "false-negative": 0, "precision": 0.0, "recall": 0.0, "f1-score": 0.0, "supports": 0}, "XOR Gateway": {"true-positive": 0, "false-positive": 0, "true-negative": 0, "false-negative": 4, "precision": 0.0, "recall": 0.0, "f1-score": 0.0, "supports": 4}, "AND Gateway": {"true-positive": 0, "false-positive": 0, "true-negative": 0, "false-negative": 1, "precision": 0.0, "recall": 0.0, "f1-score": 0.0, "supports": 1}, "Condition Specification": {"true-positive": 0, "false-positive": 0, "true-negative": 0, "false-negative": 3, "precision": 0.0, "recall": 0.0, "f1-score": 0.0, "supports": 3}}, "doc-5.2": {"Activity": {"true-positive": 1, "false-positive": 12, "true-negative": 0, "false-negative": 6, "precision": 0.07692307692307693, "recall": 0.14285714285714285, "f1-score": 0.1, "supports": 7}, "Activity Data": {"true-positive": 6, "false-positive": 7, "true-negative": 0, "false-negative": 1, "precision": 0.46153846153846156, "recall": 0.8571428571428571, "f1-score": 0.6, "supports": 7}, "Actor": {"true-positive": 0, "false-positive": 0, "true-negative": 0, "false-negative": 6, "precision": 0.0, "recall": 0.0, "f1-score": 0.0, "supports": 6}, "Further Specification": {"true-positive": 0, "false-positive": 0, "true-negative": 0, "false-negative": 0, "precision": 0.0, "recall": 0.0, "f1-score": 0.0, "supports": 0}, "XOR Gateway": {"true-positive": 0, "false-positive": 0, "true-negative": 0, "false-negative": 2, "precision": 0.0, "recall": 0.0, "f1-score": 0.0, "supports": 2}, "AND Gateway": {"true-positive": 0, "false-positive": 0, "true-negative": 0, "false-negative": 0, "precision": 0.0, "recall": 0.0, "f1-score": 0.0, "supports": 0}, "Condition Specification": {"true-positive": 0, "false-positive": 0, "true-negative": 0, "false-negative": 2, "precision": 0.0, "recall": 0.0, "f1-score": 0.0, "supports": 2}}, "doc-2.1": {"Activity": {"true-positive": 0, "false-positive": 5, "true-negative": 0, "false-negative": 42, "precision": 0.0, "recall": 0.0, "f1-score": 0.0, "supports": 42}, "Activity Data": {"true-positive": 2, "false-positive": 3, "true-negative": 0, "false-negative": 41, "precision": 0.4, "recall": 0.046511627906976744, "f1-score": 0.08333333333333333, "supports": 43}, "Actor": {"true-positive": 0, "false-positive": 0, "true-negative": 0, "false-negative": 28, "precision": 0.0, "recall": 0.0, "f1-score": 0.0, "supports": 28}, "Further Specification": {"true-positive": 0, "false-positive": 0, "true-negative": 0, "false-negative": 2, "precision": 0.0, "recall": 0.0, "f1-score": 0.0, "supports": 2}, "XOR Gateway": {"true-positive": 0, "false-positive": 0, "true-negative": 0, "false-negative": 10, "precision": 0.0, "recall": 0.0, "f1-score": 0.0, "supports": 10}, "AND Gateway": {"true-positive": 0, "false-positive": 0, "true-negative": 0, "false-negative": 1, "precision": 0.0, "recall": 0.0, "f1-score": 0.0, "supports": 1}, "Condition Specification": {"true-positive": 0, "false-positive": 0, "true-negative": 0, "false-negative": 9, "precision": 0.0, "recall": 0.0, "f1-score": 0.0, "supports": 9}}, "doc-1.2": {"Activity": {"true-positive": 2, "false-positive": 12, "true-negative": 0, "false-negative": 8, "precision": 0.14285714285714285, "recall": 0.2, "f1-score": 0.16666666666666666, "supports": 10}, "Activity Data": {"true-positive": 3, "false-positive": 11, "true-negative": 0, "false-negative": 5, "precision": 0.21428571428571427, "recall": 0.375, "f1-score": 0.2727272727272727, "supports": 8}, "Actor": {"true-positive": 0, "false-positive": 0, "true-negative": 0, "false-negative": 3, "precision": 0.0, "recall": 0.0, "f1-score": 0.0, "supports": 3}, "Further Specification": {"true-positive": 0, "false-positive": 0, "true-negative": 0, "false-negative": 1, "precision": 0.0, "recall": 0.0, "f1-score": 0.0, "supports": 1}, "XOR Gateway": {"true-positive": 0, "false-positive": 0, "true-negative": 0, "false-negative": 4, "precision": 0.0, "recall": 0.0, "f1-score": 0.0, "supports": 4}, "AND Gateway": {"true-positive": 0, "false-positive": 0, "true-negative": 0, "false-negative": 1, "precision": 0.0, "recall": 0.0, "f1-score": 0.0, "supports": 1}, "Condition Specification": {"true-positive": 0, "false-positive": 0, "true-negative": 0, "false-negative": 2, "precision": 0.0, "recall": 0.0, "f1-score": 0.0, "supports": 2}}, "doc-10.12": {"Activity": {"true-positive": 2, "false-positive": 3, "true-negative": 0, "false-negative": 3, "precision": 0.4, "recall": 0.4, "f1-score": 0.4000000000000001, "supports": 5}, "Activity Data": {"true-positive": 0, "false-positive": 5, "true-negative": 0, "false-negative": 4, "precision": 0.0, "recall": 0.0, "f1-score": 0.0, "supports": 4}, "Actor": {"true-positive": 0, "false-positive": 0, "true-negative": 0, "false-negative": 7, "precision": 0.0, "recall": 0.0, "f1-score": 0.0, "supports": 7}, "Further Specification": {"true-positive": 0, "false-positive": 0, "true-negative": 0, "false-negative": 1, "precision": 0.0, "recall": 0.0, "f1-score": 0.0, "supports": 1}, "XOR Gateway": {"true-positive": 0, "false-positive": 0, "true-negative": 0, "false-negative": 1, "precision": 0.0, "recall": 0.0, "f1-score": 0.0, "supports": 1}, "AND Gateway": {"true-positive": 0, "false-positive": 0, "true-negative": 0, "false-negative": 0, "precision": 0.0, "recall": 0.0, "f1-score": 0.0, "supports": 0}, "Condition Specification": {"true-positive": 0, "false-positive": 0, "true-negative": 0, "false-negative": 0, "precision": 0.0, "recall": 0.0, "f1-score": 0.0, "supports": 0}}, "doc-10.6": {"Activity": {"true-positive": 1, "false-positive": 3, "true-negative": 0, "false-negative": 3, "precision": 0.25, "recall": 0.25, "f1-score": 0.25, "supports": 4}, "Activity Data": {"true-positive": 2, "false-positive": 2, "true-negative": 0, "false-negative": 2, "precision": 0.5, "recall": 0.5, "f1-score": 0.5, "supports": 4}, "Actor": {"true-positive": 0, "false-positive": 0, "true-negative": 0, "false-negative": 5, "precision": 0.0, "recall": 0.0, "f1-score": 0.0, "supports": 5}, "Further Specification": {"true-positive": 0, "false-positive": 0, "true-negative": 0, "false-negative": 0, "precision": 0.0, "recall": 0.0, "f1-score": 0.0, "supports": 0}, "XOR Gateway": {"true-positive": 0, "false-positive": 0, "true-negative": 0, "false-negative": 1, "precision": 0.0, "recall": 0.0, "f1-score": 0.0, "supports": 1}, "AND Gateway": {"true-positive": 0, "false-positive": 0, "true-negative": 0, "false-negative": 0, "precision": 0.0, "recall": 0.0, "f1-score": 0.0, "supports": 0}, "Condition Specification": {"true-positive": 0, "false-positive": 0, "true-negative": 0, "false-negative": 0, "precision": 0.0, "recall": 0.0, "f1-score": 0.0, "supports": 0}}, "doc-5.3": {"Activity": {"true-positive": 6, "false-positive": 22, "true-negative": 0, "false-negative": 10, "precision": 0.21428571428571427, "recall": 0.375, "f1-score": 0.2727272727272727, "supports": 16}, "Activity Data": {"true-positive": 8, "false-positive": 25, "true-negative": 0, "false-negative": 7, "precision": 0.24242424242424243, "recall": 0.5333333333333333, "f1-score": 0.3333333333333333, "supports": 15}, "Actor": {"true-positive": 0, "false-positive": 0, "true-negative": 0, "false-negative": 9, "precision": 0.0, "recall": 0.0, "f1-score": 0.0, "supports": 9}, "Further Specification": {"true-positive": 0, "false-positive": 0, "true-negative": 0, "false-negative": 0, "precision": 0.0, "recall": 0.0, "f1-score": 0.0, "supports": 0}, "XOR Gateway": {"true-positive": 0, "false-positive": 0, "true-negative": 0, "false-negative": 4, "precision": 0.0, "recall": 0.0, "f1-score": 0.0, "supports": 4}, "AND Gateway": {"true-positive": 0, "false-positive": 0, "true-negative": 0, "false-negative": 0, "precision": 0.0, "recall": 0.0, "f1-score": 0.0, "supports": 0}, "Condition Specification": {"true-positive": 0, "false-positive": 0, "true-negative": 0, "false-negative": 4, "precision": 0.0, "recall": 0.0, "f1-score": 0.0, "supports": 4}}, "doc-10.9": {"Activity": {"true-positive": 1, "false-positive": 5, "true-negative": 0, "false-negative": 7, "precision": 0.16666666666666666, "recall": 0.125, "f1-score": 0.14285714285714288, "supports": 8}, "Activity Data": {"true-positive": 3, "false-positive": 3, "true-negative": 0, "false-negative": 5, "precision": 0.5, "recall": 0.375, "f1-score": 0.42857142857142855, "supports": 8}, "Actor": {"true-positive": 0, "false-positive": 0, "true-negative": 0, "false-negative": 10, "precision": 0.0, "recall": 0.0, "f1-score": 0.0, "supports": 10}, "Further Specification": {"true-positive": 0, "false-positive": 0, "true-negative": 0, "false-negative": 0, "precision": 0.0, "recall": 0.0, "f1-score": 0.0, "supports": 0}, "XOR Gateway": {"true-positive": 0, "false-positive": 0, "true-negative": 0, "false-negative": 3, "precision": 0.0, "recall": 0.0, "f1-score": 0.0, "supports": 3}, "AND Gateway": {"true-positive": 0, "false-positive": 0, "true-negative": 0, "false-negative": 0, "precision": 0.0, "recall": 0.0, "f1-score": 0.0, "supports": 0}, "Condition Specification": {"true-positive": 0, "false-positive": 0, "true-negative": 0, "false-negative": 0, "precision": 0.0, "recall": 0.0, "f1-score": 0.0, "supports": 0}}, "doc-3.5": {"Activity": {"true-positive": 0, "false-positive": 16, "true-negative": 0, "false-negative": 17, "precision": 0.0, "recall": 0.0, "f1-score": 0.0, "supports": 17}, "Activity Data": {"true-positive": 5, "false-positive": 11, "true-negative": 0, "false-negative": 6, "precision": 0.3125, "recall": 0.45454545454545453, "f1-score": 0.3703703703703703, "supports": 11}, "Actor": {"true-positive": 0, "false-positive": 0, "true-negative": 0, "false-negative": 10, "precision": 0.0, "recall": 0.0, "f1-score": 0.0, "supports": 10}, "Further Specification": {"true-positive": 0, "false-positive": 0, "true-negative": 0, "false-negative": 3, "precision": 0.0, "recall": 0.0, "f1-score": 0.0, "supports": 3}, "XOR Gateway": {"true-positive": 0, "false-positive": 0, "true-negative": 0, "false-negative": 2, "precision": 0.0, "recall": 0.0, "f1-score": 0.0, "supports": 2}, "AND Gateway": {"true-positive": 0, "false-positive": 0, "true-negative": 0, "false-negative": 1, "precision": 0.0, "recall": 0.0, "f1-score": 0.0, "supports": 1}, "Condition Specification": {"true-positive": 0, "false-positive": 0, "true-negative": 0, "false-negative": 1, "precision": 0.0, "recall": 0.0, "f1-score": 0.0, "supports": 1}}, "doc-3.3": {"Activity": {"true-positive": 1, "false-positive": 5, "true-negative": 0, "false-negative": 6, "precision": 0.16666666666666666, "recall": 0.14285714285714285, "f1-score": 0.15384615384615383, "supports": 7}, "Activity Data": {"true-positive": 4, "false-positive": 2, "true-negative": 0, "false-negative": 3, "precision": 0.6666666666666666, "recall": 0.5714285714285714, "f1-score": 0.6153846153846153, "supports": 7}, "Actor": {"true-positive": 0, "false-positive": 0, "true-negative": 0, "false-negative": 4, "precision": 0.0, "recall": 0.0, "f1-score": 0.0, "supports": 4}, "Further Specification": {"true-positive": 0, "false-positive": 0, "true-negative": 0, "false-negative": 1, "precision": 0.0, "recall": 0.0, "f1-score": 0.0, "supports": 1}, "XOR Gateway": {"true-positive": 0, "false-positive": 0, "true-negative": 0, "false-negative": 2, "precision": 0.0, "recall": 0.0, "f1-score": 0.0, "supports": 2}, "AND Gateway": {"true-positive": 0, "false-positive": 0, "true-negative": 0, "false-negative": 0, "precision": 0.0, "recall": 0.0, "f1-score": 0.0, "supports": 0}, "Condition Specification": {"true-positive": 0, "false-positive": 0, "true-negative": 0, "false-negative": 2, "precision": 0.0, "recall": 0.0, "f1-score": 0.0, "supports": 2}}, "doc-10.14": {"Activity": {"true-positive": 0, "false-positive": 10, "true-negative": 0, "false-negative": 10, "precision": 0.0, "recall": 0.0, "f1-score": 0.0, "supports": 10}, "Activity Data": {"true-positive": 4, "false-positive": 6, "true-negative": 0, "false-negative": 6, "precision": 0.4, "recall": 0.4, "f1-score": 0.4000000000000001, "supports": 10}, "Actor": {"true-positive": 0, "false-positive": 0, "true-negative": 0, "false-negative": 15, "precision": 0.0, "recall": 0.0, "f1-score": 0.0, "supports": 15}, "Further Specification": {"true-positive": 0, "false-positive": 0, "true-negative": 0, "false-negative": 0, "precision": 0.0, "recall": 0.0, "f1-score": 0.0, "supports": 0}, "XOR Gateway": {"true-positive": 0, "false-positive": 0, "true-negative": 0, "false-negative": 5, "precision": 0.0, "recall": 0.0, "f1-score": 0.0, "supports": 5}, "AND Gateway": {"true-positive": 0, "false-positive": 0, "true-negative": 0, "false-negative": 0, "precision": 0.0, "recall": 0.0, "f1-score": 0.0, "supports": 0}, "Condition Specification": {"true-positive": 0, "false-positive": 0, "true-negative": 0, "false-negative": 0, "precision": 0.0, "recall": 0.0, "f1-score": 0.0, "supports": 0}}, "doc-10.5": {"Activity": {"true-positive": 0, "false-positive": 3, "true-negative": 0, "false-negative": 5, "precision": 0.0, "recall": 0.0, "f1-score": 0.0, "supports": 5}, "Activity Data": {"true-positive": 1, "false-positive": 2, "true-negative": 0, "false-negative": 4, "precision": 0.3333333333333333, "recall": 0.2, "f1-score": 0.25, "supports": 5}, "Actor": {"true-positive": 0, "false-positive": 0, "true-negative": 0, "false-negative": 7, "precision": 0.0, "recall": 0.0, "f1-score": 0.0, "supports": 7}, "Further Specification": {"true-positive": 0, "false-positive": 0, "true-negative": 0, "false-negative": 0, "precision": 0.0, "recall": 0.0, "f1-score": 0.0, "supports": 0}, "XOR Gateway": {"true-positive": 0, "false-positive": 0, "true-negative": 0, "false-negative": 0, "precision": 0.0, "recall": 0.0, "f1-score": 0.0, "supports": 0}, "AND Gateway": {"true-positive": 0, "false-positive": 0, "true-negative": 0, "false-negative": 0, "precision": 0.0, "recall": 0.0, "f1-score": 0.0, "supports": 0}, "Condition Specification": {"true-positive": 0, "false-positive": 0, "true-negative": 0, "false-negative": 0, "precision": 0.0, "recall": 0.0, "f1-score": 0.0, "supports": 0}}, "doc-9.2": {"Activity": {"true-positive": 1, "false-positive": 10, "true-negative": 0, "false-negative": 9, "precision": 0.09090909090909091, "recall": 0.1, "f1-score": 0.09523809523809525, "supports": 10}, "Activity Data": {"true-positive": 4, "false-positive": 8, "true-negative": 0, "false-negative": 3, "precision": 0.3333333333333333, "recall": 0.5714285714285714, "f1-score": 0.4210526315789474, "supports": 7}, "Actor": {"true-positive": 0, "false-positive": 0, "true-negative": 0, "false-negative": 4, "precision": 0.0, "recall": 0.0, "f1-score": 0.0, "supports": 4}, "Further Specification": {"true-positive": 0, "false-positive": 0, "true-negative": 0, "false-negative": 1, "precision": 0.0, "recall": 0.0, "f1-score": 0.0, "supports": 1}, "XOR Gateway": {"true-positive": 0, "false-positive": 0, "true-negative": 0, "false-negative": 4, "precision": 0.0, "recall": 0.0, "f1-score": 0.0, "supports": 4}, "AND Gateway": {"true-positive": 0, "false-positive": 0, "true-negative": 0, "false-negative": 0, "precision": 0.0, "recall": 0.0, "f1-score": 0.0, "supports": 0}, "Condition Specification": {"true-positive": 0, "false-positive": 0, "true-negative": 0, "false-negative": 4, "precision": 0.0, "recall": 0.0, "f1-score": 0.0, "supports": 4}}, "doc-10.8": {"Activity": {"true-positive": 0, "false-positive": 7, "true-negative": 0, "false-negative": 8, "precision": 0.0, "recall": 0.0, "f1-score": 0.0, "supports": 8}, "Activity Data": {"true-positive": 2, "false-positive": 5, "true-negative": 0, "false-negative": 5, "precision": 0.2857142857142857, "recall": 0.2857142857142857, "f1-score": 0.2857142857142857, "supports": 7}, "Actor": {"true-positive": 0, "false-positive": 0, "true-negative": 0, "false-negative": 12, "precision": 0.0, "recall": 0.0, "f1-score": 0.0, "supports": 12}, "Further Specification": {"true-positive": 0, "false-positive": 0, "true-negative": 0, "false-negative": 2, "precision": 0.0, "recall": 0.0, "f1-score": 0.0, "supports": 2}, "XOR Gateway": {"true-positive": 0, "false-positive": 0, "true-negative": 0, "false-negative": 1, "precision": 0.0, "recall": 0.0, "f1-score": 0.0, "supports": 1}, "AND Gateway": {"true-positive": 0, "false-positive": 0, "true-negative": 0, "false-negative": 0, "precision": 0.0, "recall": 0.0, "f1-score": 0.0, "supports": 0}, "Condition Specification": {"true-positive": 0, "false-positive": 0, "true-negative": 0, "false-negative": 0, "precision": 0.0, "recall": 0.0, "f1-score": 0.0, "supports": 0}}, "doc-4.1": {"Activity": {"true-positive": 5, "false-positive": 51, "true-negative": 0, "false-negative": 30, "precision": 0.08928571428571429, "recall": 0.14285714285714285, "f1-score": 0.10989010989010989, "supports": 35}, "Activity Data": {"true-positive": 11, "false-positive": 47, "true-negative": 0, "false-negative": 19, "precision": 0.1896551724137931, "recall": 0.36666666666666664, "f1-score": 0.25, "supports": 30}, "Actor": {"true-positive": 0, "false-positive": 0, "true-negative": 0, "false-negative": 24, "precision": 0.0, "recall": 0.0, "f1-score": 0.0, "supports": 24}, "Further Specification": {"true-positive": 0, "false-positive": 0, "true-negative": 0, "false-negative": 17, "precision": 0.0, "recall": 0.0, "f1-score": 0.0, "supports": 17}, "XOR Gateway": {"true-positive": 0, "false-positive": 0, "true-negative": 0, "false-negative": 3, "precision": 0.0, "recall": 0.0, "f1-score": 0.0, "supports": 3}, "AND Gateway": {"true-positive": 0, "false-positive": 0, "true-negative": 0, "false-negative": 0, "precision": 0.0, "recall": 0.0, "f1-score": 0.0, "supports": 0}, "Condition Specification": {"true-positive": 0, "false-positive": 0, "true-negative": 0, "false-negative": 3, "precision": 0.0, "recall": 0.0, "f1-score": 0.0, "supports": 3}}, "doc-10.13": {"Activity": {"true-positive": 0, "false-positive": 2, "true-negative": 0, "false-negative": 3, "precision": 0.0, "recall": 0.0, "f1-score": 0.0, "supports": 3}, "Activity Data": {"true-positive": 0, "false-positive": 2, "true-negative": 0, "false-negative": 3, "precision": 0.0, "recall": 0.0, "f1-score": 0.0, "supports": 3}, "Actor": {"true-positive": 0, "false-positive": 0, "true-negative": 0, "false-negative": 4, "precision": 0.0, "recall": 0.0, "f1-score": 0.0, "supports": 4}, "Further Specification": {"true-positive": 0, "false-positive": 0, "true-negative": 0, "false-negative": 1, "precision": 0.0, "recall": 0.0, "f1-score": 0.0, "supports": 1}, "XOR Gateway": {"true-positive": 0, "false-positive": 0, "true-negative": 0, "false-negative": 0, "precision": 0.0, "recall": 0.0, "f1-score": 0.0, "supports": 0}, "AND Gateway": {"true-positive": 0, "false-positive": 0, "true-negative": 0, "false-negative": 0, "precision": 0.0, "recall": 0.0, "f1-score": 0.0, "supports": 0}, "Condition Specification": {"true-positive": 0, "false-positive": 0, "true-negative": 0, "false-negative": 0, "precision": 0.0, "recall": 0.0, "f1-score": 0.0, "supports": 0}}, "doc-6.1": {"Activity": {"true-positive": 1, "false-positive": 30, "true-negative": 0, "false-negative": 28, "precision": 0.03225806451612903, "recall": 0.034482758620689655, "f1-score": 0.03333333333333333, "supports": 29}, "Activity Data": {"true-positive": 6, "false-positive": 30, "true-negative": 0, "false-negative": 18, "precision": 0.16666666666666666, "recall": 0.25, "f1-score": 0.2, "supports": 24}, "Actor": {"true-positive": 0, "false-positive": 0, "true-negative": 0, "false-negative": 24, "precision": 0.0, "recall": 0.0, "f1-score": 0.0, "supports": 24}, "Further Specification": {"true-positive": 0, "false-positive": 0, "true-negative": 0, "false-negative": 4, "precision": 0.0, "recall": 0.0, "f1-score": 0.0, "supports": 4}, "XOR Gateway": {"true-positive": 0, "false-positive": 0, "true-negative": 0, "false-negative": 6, "precision": 0.0, "recall": 0.0, "f1-score": 0.0, "supports": 6}, "AND Gateway": {"true-positive": 0, "false-positive": 0, "true-negative": 0, "false-negative": 0, "precision": 0.0, "recall": 0.0, "f1-score": 0.0, "supports": 0}, "Condition Specification": {"true-positive": 0, "false-positive": 0, "true-negative": 0, "false-negative": 6, "precision": 0.0, "recall": 0.0, "f1-score": 0.0, "supports": 6}}, "doc-5.1": {"Activity": {"true-positive": 1, "false-positive": 8, "true-negative": 0, "false-negative": 5, "precision": 0.1111111111111111, "recall": 0.16666666666666666, "f1-score": 0.13333333333333333, "supports": 6}, "Activity Data": {"true-positive": 5, "false-positive": 5, "true-negative": 0, "false-negative": 0, "precision": 0.5, "recall": 1.0, "f1-score": 0.6666666666666666, "supports": 5}, "Actor": {"true-positive": 0, "false-positive": 0, "true-negative": 0, "false-negative": 4, "precision": 0.0, "recall": 0.0, "f1-score": 0.0, "supports": 4}, "Further Specification": {"true-positive": 0, "false-positive": 0, "true-negative": 0, "false-negative": 0, "precision": 0.0, "recall": 0.0, "f1-score": 0.0, "supports": 0}, "XOR Gateway": {"true-positive": 0, "false-positive": 0, "true-negative": 0, "false-negative": 3, "precision": 0.0, "recall": 0.0, "f1-score": 0.0, "supports": 3}, "AND Gateway": {"true-positive": 0, "false-positive": 0, "true-negative": 0, "false-negative": 0, "precision": 0.0, "recall": 0.0, "f1-score": 0.0, "supports": 0}, "Condition Specification": {"true-positive": 0, "false-positive": 0, "true-negative": 0, "false-negative": 3, "precision": 0.0, "recall": 0.0, "f1-score": 0.0, "supports": 3}}, "doc-6.3": {"Activity": {"true-positive": 1, "false-positive": 11, "true-negative": 0, "false-negative": 8, "precision": 0.08333333333333333, "recall": 0.1111111111111111, "f1-score": 0.09523809523809525, "supports": 9}, "Activity Data": {"true-positive": 2, "false-positive": 10, "true-negative": 0, "false-negative": 6, "precision": 0.16666666666666666, "recall": 0.25, "f1-score": 0.2, "supports": 8}, "Actor": {"true-positive": 0, "false-positive": 0, "true-negative": 0, "false-negative": 5, "precision": 0.0, "recall": 0.0, "f1-score": 0.0, "supports": 5}, "Further Specification": {"true-positive": 0, "false-positive": 0, "true-negative": 0, "false-negative": 2, "precision": 0.0, "recall": 0.0, "f1-score": 0.0, "supports": 2}, "XOR Gateway": {"true-positive": 0, "false-positive": 0, "true-negative": 0, "false-negative": 1, "precision": 0.0, "recall": 0.0, "f1-score": 0.0, "supports": 1}, "AND Gateway": {"true-positive": 0, "false-positive": 0, "true-negative": 0, "false-negative": 0, "precision": 0.0, "recall": 0.0, "f1-score": 0.0, "supports": 0}, "Condition Specification": {"true-positive": 0, "false-positive": 0, "true-negative": 0, "false-negative": 1, "precision": 0.0, "recall": 0.0, "f1-score": 0.0, "supports": 1}}, "doc-3.8": {"Activity": {"true-positive": 0, "false-positive": 13, "true-negative": 0, "false-negative": 10, "precision": 0.0, "recall": 0.0, "f1-score": 0.0, "supports": 10}, "Activity Data": {"true-positive": 7, "false-positive": 6, "true-negative": 0, "false-negative": 2, "precision": 0.5384615384615384, "recall": 0.7777777777777778, "f1-score": 0.6363636363636364, "supports": 9}, "Actor": {"true-positive": 0, "false-positive": 0, "true-negative": 0, "false-negative": 5, "precision": 0.0, "recall": 0.0, "f1-score": 0.0, "supports": 5}, "Further Specification": {"true-positive": 0, "false-positive": 0, "true-negative": 0, "false-negative": 3, "precision": 0.0, "recall": 0.0, "f1-score": 0.0, "supports": 3}, "XOR Gateway": {"true-positive": 0, "false-positive": 0, "true-negative": 0, "false-negative": 2, "precision": 0.0, "recall": 0.0, "f1-score": 0.0, "supports": 2}, "AND Gateway": {"true-positive": 0, "false-positive": 0, "true-negative": 0, "false-negative": 0, "precision": 0.0, "recall": 0.0, "f1-score": 0.0, "supports": 0}, "Condition Specification": {"true-positive": 0, "false-positive": 0, "true-negative": 0, "false-negative": 1, "precision": 0.0, "recall": 0.0, "f1-score": 0.0, "supports": 1}}, "doc-3.1": {"Activity": {"true-positive": 0, "false-positive": 12, "true-negative": 0, "false-negative": 11, "precision": 0.0, "recall": 0.0, "f1-score": 0.0, "supports": 11}, "Activity Data": {"true-positive": 5, "false-positive": 10, "true-negative": 0, "false-negative": 6, "precision": 0.3333333333333333, "recall": 0.45454545454545453, "f1-score": 0.3846153846153846, "supports": 11}, "Actor": {"true-positive": 0, "false-positive": 0, "true-negative": 0, "false-negative": 6, "precision": 0.0, "recall": 0.0, "f1-score": 0.0, "supports": 6}, "Further Specification": {"true-positive": 0, "false-positive": 0, "true-negative": 0, "false-negative": 1, "precision": 0.0, "recall": 0.0, "f1-score": 0.0, "supports": 1}, "XOR Gateway": {"true-positive": 0, "false-positive": 0, "true-negative": 0, "false-negative": 0, "precision": 0.0, "recall": 0.0, "f1-score": 0.0, "supports": 0}, "AND Gateway": {"true-positive": 0, "false-positive": 0, "true-negative": 0, "false-negative": 0, "precision": 0.0, "recall": 0.0, "f1-score": 0.0, "supports": 0}, "Condition Specification": {"true-positive": 0, "false-positive": 0, "true-negative": 0, "false-negative": 0, "precision": 0.0, "recall": 0.0, "f1-score": 0.0, "supports": 0}}, "doc-3.6": {"Activity": {"true-positive": 0, "false-positive": 12, "true-negative": 0, "false-negative": 9, "precision": 0.0, "recall": 0.0, "f1-score": 0.0, "supports": 9}, "Activity Data": {"true-positive": 2, "false-positive": 11, "true-negative": 0, "false-negative": 6, "precision": 0.15384615384615385, "recall": 0.25, "f1-score": 0.1904761904761905, "supports": 8}, "Actor": {"true-positive": 0, "false-positive": 0, "true-negative": 0, "false-negative": 3, "precision": 0.0, "recall": 0.0, "f1-score": 0.0, "supports": 3}, "Further Specification": {"true-positive": 0, "false-positive": 0, "true-negative": 0, "false-negative": 3, "precision": 0.0, "recall": 0.0, "f1-score": 0.0, "supports": 3}, "XOR Gateway": {"true-positive": 0, "false-positive": 0, "true-negative": 0, "false-negative": 4, "precision": 0.0, "recall": 0.0, "f1-score": 0.0, "supports": 4}, "AND Gateway": {"true-positive": 0, "false-positive": 0, "true-negative": 0, "false-negative": 0, "precision": 0.0, "recall": 0.0, "f1-score": 0.0, "supports": 0}, "Condition Specification": {"true-positive": 0, "false-positive": 0, "true-negative": 0, "false-negative": 2, "precision": 0.0, "recall": 0.0, "f1-score": 0.0, "supports": 2}}, "doc-10.3": {"Activity": {"true-positive": 1, "false-positive": 12, "true-negative": 0, "false-negative": 10, "precision": 0.07692307692307693, "recall": 0.09090909090909091, "f1-score": 0.08333333333333334, "supports": 11}, "Activity Data": {"true-positive": 2, "false-positive": 13, "true-negative": 0, "false-negative": 8, "precision": 0.13333333333333333, "recall": 0.2, "f1-score": 0.16, "supports": 10}, "Actor": {"true-positive": 0, "false-positive": 0, "true-negative": 0, "false-negative": 16, "precision": 0.0, "recall": 0.0, "f1-score": 0.0, "supports": 16}, "Further Specification": {"true-positive": 0, "false-positive": 0, "true-negative": 0, "false-negative": 1, "precision": 0.0, "recall": 0.0, "f1-score": 0.0, "supports": 1}, "XOR Gateway": {"true-positive": 0, "false-positive": 0, "true-negative": 0, "false-negative": 2, "precision": 0.0, "recall": 0.0, "f1-score": 0.0, "supports": 2}, "AND Gateway": {"true-positive": 0, "false-positive": 0, "true-negative": 0, "false-negative": 0, "precision": 0.0, "recall": 0.0, "f1-score": 0.0, "supports": 0}, "Condition Specification": {"true-positive": 0, "false-positive": 0, "true-negative": 0, "false-negative": 1, "precision": 0.0, "recall": 0.0, "f1-score": 0.0, "supports": 1}}, "doc-5.4": {"Activity": {"true-positive": 1, "false-positive": 29, "true-negative": 0, "false-negative": 9, "precision": 0.03333333333333333, "recall": 0.1, "f1-score": 0.05, "supports": 10}, "Activity Data": {"true-positive": 7, "false-positive": 24, "true-negative": 0, "false-negative": 3, "precision": 0.22580645161290322, "recall": 0.7, "f1-score": 0.3414634146341463, "supports": 10}, "Actor": {"true-positive": 0, "false-positive": 0, "true-negative": 0, "false-negative": 9, "precision": 0.0, "recall": 0.0, "f1-score": 0.0, "supports": 9}, "Further Specification": {"true-positive": 0, "false-positive": 0, "true-negative": 0, "false-negative": 0, "precision": 0.0, "recall": 0.0, "f1-score": 0.0, "supports": 0}, "XOR Gateway": {"true-positive": 0, "false-positive": 0, "true-negative": 0, "false-negative": 4, "precision": 0.0, "recall": 0.0, "f1-score": 0.0, "supports": 4}, "AND Gateway": {"true-positive": 0, "false-positive": 0, "true-negative": 0, "false-negative": 0, "precision": 0.0, "recall": 0.0, "f1-score": 0.0, "supports": 0}, "Condition Specification": {"true-positive": 0, "false-positive": 0, "true-negative": 0, "false-negative": 4, "precision": 0.0, "recall": 0.0, "f1-score": 0.0, "supports": 4}}, "doc-9.5": {"Activity": {"true-positive": 3, "false-positive": 13, "true-negative": 0, "false-negative": 7, "precision": 0.1875, "recall": 0.3, "f1-score": 0.23076923076923075, "supports": 10}, "Activity Data": {"true-positive": 5, "false-positive": 12, "true-negative": 0, "false-negative": 4, "precision": 0.29411764705882354, "recall": 0.5555555555555556, "f1-score": 0.3846153846153846, "supports": 9}, "Actor": {"true-positive": 0, "false-positive": 0, "true-negative": 0, "false-negative": 4, "precision": 0.0, "recall": 0.0, "f1-score": 0.0, "supports": 4}, "Further Specification": {"true-positive": 0, "false-positive": 0, "true-negative": 0, "false-negative": 4, "precision": 0.0, "recall": 0.0, "f1-score": 0.0, "supports": 4}, "XOR Gateway": {"true-positive": 0, "false-positive": 0, "true-negative": 0, "false-negative": 6, "precision": 0.0, "recall": 0.0, "f1-score": 0.0, "supports": 6}, "AND Gateway": {"true-positive": 0, "false-positive": 0, "true-negative": 0, "false-negative": 0, "precision": 0.0, "recall": 0.0, "f1-score": 0.0, "supports": 0}, "Condition Specification": {"true-positive": 0, "false-positive": 0, "true-negative": 0, "false-negative": 6, "precision": 0.0, "recall": 0.0, "f1-score": 0.0, "supports": 6}}, "doc-1.3": {"Activity": {"true-positive": 0, "false-positive": 4, "true-negative": 0, "false-negative": 11, "precision": 0.0, "recall": 0.0, "f1-score": 0.0, "supports": 11}, "Activity Data": {"true-positive": 1, "false-positive": 6, "true-negative": 0, "false-negative": 8, "precision": 0.14285714285714285, "recall": 0.1111111111111111, "f1-score": 0.125, "supports": 9}, "Actor": {"true-positive": 0, "false-positive": 0, "true-negative": 0, "false-negative": 16, "precision": 0.0, "recall": 0.0, "f1-score": 0.0, "supports": 16}, "Further Specification": {"true-positive": 0, "false-positive": 0, "true-negative": 0, "false-negative": 3, "precision": 0.0, "recall": 0.0, "f1-score": 0.0, "supports": 3}, "XOR Gateway": {"true-positive": 0, "false-positive": 0, "true-negative": 0, "false-negative": 1, "precision": 0.0, "recall": 0.0, "f1-score": 0.0, "supports": 1}, "AND Gateway": {"true-positive": 0, "false-positive": 0, "true-negative": 0, "false-negative": 1, "precision": 0.0, "recall": 0.0, "f1-score": 0.0, "supports": 1}, "Condition Specification": {"true-positive": 0, "false-positive": 0, "true-negative": 0, "false-negative": 1, "precision": 0.0, "recall": 0.0, "f1-score": 0.0, "supports": 1}}, "doc-10.4": {"Activity": {"true-positive": 4, "false-positive": 3, "true-negative": 0, "false-negative": 6, "precision": 0.5714285714285714, "recall": 0.4, "f1-score": 0.47058823529411764, "supports": 10}, "Activity Data": {"true-positive": 1, "false-positive": 9, "true-negative": 0, "false-negative": 9, "precision": 0.1, "recall": 0.1, "f1-score": 0.10000000000000002, "supports": 10}, "Actor": {"true-positive": 0, "false-positive": 0, "true-negative": 0, "false-negative": 16, "precision": 0.0, "recall": 0.0, "f1-score": 0.0, "supports": 16}, "Further Specification": {"true-positive": 0, "false-positive": 0, "true-negative": 0, "false-negative": 0, "precision": 0.0, "recall": 0.0, "f1-score": 0.0, "supports": 0}, "XOR Gateway": {"true-positive": 0, "false-positive": 0, "true-negative": 0, "false-negative": 1, "precision": 0.0, "recall": 0.0, "f1-score": 0.0, "supports": 1}, "AND Gateway": {"true-positive": 0, "false-positive": 0, "true-negative": 0, "false-negative": 0, "precision": 0.0, "recall": 0.0, "f1-score": 0.0, "supports": 0}, "Condition Specification": {"true-positive": 0, "false-positive": 0, "true-negative": 0, "false-negative": 0, "precision": 0.0, "recall": 0.0, "f1-score": 0.0, "supports": 0}}, "doc-8.3": {"Activity": {"true-positive": 3, "false-positive": 2, "true-negative": 0, "false-negative": 3, "precision": 0.6, "recall": 0.5, "f1-score": 0.5454545454545454, "supports": 6}, "Activity Data": {"true-positive": 3, "false-positive": 4, "true-negative": 0, "false-negative": 3, "precision": 0.42857142857142855, "recall": 0.5, "f1-score": 0.4615384615384615, "supports": 6}, "Actor": {"true-positive": 0, "false-positive": 0, "true-negative": 0, "false-negative": 6, "precision": 0.0, "recall": 0.0, "f1-score": 0.0, "supports": 6}, "Further Specification": {"true-positive": 0, "false-positive": 0, "true-negative": 0, "false-negative": 0, "precision": 0.0, "recall": 0.0, "f1-score": 0.0, "supports": 0}, "XOR Gateway": {"true-positive": 0, "false-positive": 0, "true-negative": 0, "false-negative": 2, "precision": 0.0, "recall": 0.0, "f1-score": 0.0, "supports": 2}, "AND Gateway": {"true-positive": 0, "false-positive": 0, "true-negative": 0, "false-negative": 0, "precision": 0.0, "recall": 0.0, "f1-score": 0.0, "supports": 0}, "Condition Specification": {"true-positive": 0, "false-positive": 0, "true-negative": 0, "false-negative": 0, "precision": 0.0, "recall": 0.0, "f1-score": 0.0, "supports": 0}}, "doc-9.1": {"Activity": {"true-positive": 4, "false-positive": 16, "true-negative": 0, "false-negative": 6, "precision": 0.2, "recall": 0.4, "f1-score": 0.26666666666666666, "supports": 10}, "Activity Data": {"true-positive": 4, "false-positive": 17, "true-negative": 0, "false-negative": 5, "precision": 0.19047619047619047, "recall": 0.4444444444444444, "f1-score": 0.26666666666666666, "supports": 9}, "Actor": {"true-positive": 0, "false-positive": 0, "true-negative": 0, "false-negative": 3, "precision": 0.0, "recall": 0.0, "f1-score": 0.0, "supports": 3}, "Further Specification": {"true-positive": 0, "false-positive": 0, "true-negative": 0, "false-negative": 3, "precision": 0.0, "recall": 0.0, "f1-score": 0.0, "supports": 3}, "XOR Gateway": {"true-positive": 0, "false-positive": 0, "true-negative": 0, "false-negative": 6, "precision": 0.0, "recall": 0.0, "f1-score": 0.0, "supports": 6}, "AND Gateway": {"true-positive": 0, "false-positive": 0, "true-negative": 0, "false-negative": 0, "precision": 0.0, "recall": 0.0, "f1-score": 0.0, "supports": 0}, "Condition Specification": {"true-positive": 0, "false-positive": 0, "true-negative": 0, "false-negative": 7, "precision": 0.0, "recall": 0.0, "f1-score": 0.0, "supports": 7}}, "doc-7.1": {"Activity": {"true-positive": 0, "false-positive": 8, "true-negative": 0, "false-negative": 7, "precision": 0.0, "recall": 0.0, "f1-score": 0.0, "supports": 7}, "Activity Data": {"true-positive": 3, "false-positive": 5, "true-negative": 0, "false-negative": 4, "precision": 0.375, "recall": 0.42857142857142855, "f1-score": 0.39999999999999997, "supports": 7}, "Actor": {"true-positive": 0, "false-positive": 0, "true-negative": 0, "false-negative": 9, "precision": 0.0, "recall": 0.0, "f1-score": 0.0, "supports": 9}, "Further Specification": {"true-positive": 0, "false-positive": 0, "true-negative": 0, "false-negative": 0, "precision": 0.0, "recall": 0.0, "f1-score": 0.0, "supports": 0}, "XOR Gateway": {"true-positive": 0, "false-positive": 0, "true-negative": 0, "false-negative": 2, "precision": 0.0, "recall": 0.0, "f1-score": 0.0, "supports": 2}, "AND Gateway": {"true-positive": 0, "false-positive": 0, "true-negative": 0, "false-negative": 0, "precision": 0.0, "recall": 0.0, "f1-score": 0.0, "supports": 0}, "Condition Specification": {"true-positive": 0, "false-positive": 0, "true-negative": 0, "false-negative": 1, "precision": 0.0, "recall": 0.0, "f1-score": 0.0, "supports": 1}}, "doc-8.2": {"Activity": {"true-positive": 5, "false-positive": 5, "true-negative": 0, "false-negative": 4, "precision": 0.5, "recall": 0.5555555555555556, "f1-score": 0.5263157894736842, "supports": 9}, "Activity Data": {"true-positive": 5, "false-positive": 5, "true-negative": 0, "false-negative": 3, "precision": 0.5, "recall": 0.625, "f1-score": 0.5555555555555556, "supports": 8}, "Actor": {"true-positive": 0, "false-positive": 0, "true-negative": 0, "false-negative": 7, "precision": 0.0, "recall": 0.0, "f1-score": 0.0, "supports": 7}, "Further Specification": {"true-positive": 0, "false-positive": 0, "true-negative": 0, "false-negative": 0, "precision": 0.0, "recall": 0.0, "f1-score": 0.0, "supports": 0}, "XOR Gateway": {"true-positive": 0, "false-positive": 0, "true-negative": 0, "false-negative": 3, "precision": 0.0, "recall": 0.0, "f1-score": 0.0, "supports": 3}, "AND Gateway": {"true-positive": 0, "false-positive": 0, "true-negative": 0, "false-negative": 0, "precision": 0.0, "recall": 0.0, "f1-score": 0.0, "supports": 0}, "Condition Specification": {"true-positive": 0, "false-positive": 0, "true-negative": 0, "false-negative": 3, "precision": 0.0, "recall": 0.0, "f1-score": 0.0, "supports": 3}}, "doc-10.1": {"Activity": {"true-positive": 2, "false-positive": 2, "true-negative": 0, "false-negative": 2, "precision": 0.5, "recall": 0.5, "f1-score": 0.5, "supports": 4}, "Activity Data": {"true-positive": 2, "false-positive": 2, "true-negative": 0, "false-negative": 2, "precision": 0.5, "recall": 0.5, "f1-score": 0.5, "supports": 4}, "Actor": {"true-positive": 0, "false-positive": 0, "true-negative": 0, "false-negative": 5, "precision": 0.0, "recall": 0.0, "f1-score": 0.0, "supports": 5}, "Further Specification": {"true-positive": 0, "false-positive": 0, "true-negative": 0, "false-negative": 0, "precision": 0.0, "recall": 0.0, "f1-score": 0.0, "supports": 0}, "XOR Gateway": {"true-positive": 0, "false-positive": 0, "true-negative": 0, "false-negative": 1, "precision": 0.0, "recall": 0.0, "f1-score": 0.0, "supports": 1}, "AND Gateway": {"true-positive": 0, "false-positive": 0, "true-negative": 0, "false-negative": 0, "precision": 0.0, "recall": 0.0, "f1-score": 0.0, "supports": 0}, "Condition Specification": {"true-positive": 0, "false-positive": 0, "true-negative": 0, "false-negative": 0, "precision": 0.0, "recall": 0.0, "f1-score": 0.0, "supports": 0}}, "doc-10.11": {"Activity": {"true-positive": 0, "false-positive": 6, "true-negative": 0, "false-negative": 9, "precision": 0.0, "recall": 0.0, "f1-score": 0.0, "supports": 9}, "Activity Data": {"true-positive": 1, "false-positive": 5, "true-negative": 0, "false-negative": 8, "precision": 0.16666666666666666, "recall": 0.1111111111111111, "f1-score": 0.13333333333333333, "supports": 9}, "Actor": {"true-positive": 0, "false-positive": 0, "true-negative": 0, "false-negative": 14, "precision": 0.0, "recall": 0.0, "f1-score": 0.0, "supports": 14}, "Further Specification": {"true-positive": 0, "false-positive": 0, "true-negative": 0, "false-negative": 0, "precision": 0.0, "recall": 0.0, "f1-score": 0.0, "supports": 0}, "XOR Gateway": {"true-positive": 0, "false-positive": 0, "true-negative": 0, "false-negative": 2, "precision": 0.0, "recall": 0.0, "f1-score": 0.0, "supports": 2}, "AND Gateway": {"true-positive": 0, "false-positive": 0, "true-negative": 0, "false-negative": 0, "precision": 0.0, "recall": 0.0, "f1-score": 0.0, "supports": 0}, "Condition Specification": {"true-positive": 0, "false-positive": 0, "true-negative": 0, "false-negative": 0, "precision": 0.0, "recall": 0.0, "f1-score": 0.0, "supports": 0}}, "doc-3.7": {"Activity": {"true-positive": 1, "false-positive": 8, "true-negative": 0, "false-negative": 5, "precision": 0.1111111111111111, "recall": 0.16666666666666666, "f1-score": 0.13333333333333333, "supports": 6}, "Activity Data": {"true-positive": 3, "false-positive": 7, "true-negative": 0, "false-negative": 2, "precision": 0.3, "recall": 0.6, "f1-score": 0.4, "supports": 5}, "Actor": {"true-positive": 0, "false-positive": 0, "true-negative": 0, "false-negative": 4, "precision": 0.0, "recall": 0.0, "f1-score": 0.0, "supports": 4}, "Further Specification": {"true-positive": 0, "false-positive": 0, "true-negative": 0, "false-negative": 2, "precision": 0.0, "recall": 0.0, "f1-score": 0.0, "supports": 2}, "XOR Gateway": {"true-positive": 0, "false-positive": 0, "true-negative": 0, "false-negative": 0, "precision": 0.0, "recall": 0.0, "f1-score": 0.0, "supports": 0}, "AND Gateway": {"true-positive": 0, "false-positive": 0, "true-negative": 0, "false-negative": 0, "precision": 0.0, "recall": 0.0, "f1-score": 0.0, "supports": 0}, "Condition Specification": {"true-positive": 0, "false-positive": 0, "true-negative": 0, "false-negative": 0, "precision": 0.0, "recall": 0.0, "f1-score": 0.0, "supports": 0}}, "doc-8.1": {"Activity": {"true-positive": 1, "false-positive": 6, "true-negative": 0, "false-negative": 4, "precision": 0.14285714285714285, "recall": 0.2, "f1-score": 0.16666666666666666, "supports": 5}, "Activity Data": {"true-positive": 2, "false-positive": 5, "true-negative": 0, "false-negative": 2, "precision": 0.2857142857142857, "recall": 0.5, "f1-score": 0.36363636363636365, "supports": 4}, "Actor": {"true-positive": 0, "false-positive": 0, "true-negative": 0, "false-negative": 2, "precision": 0.0, "recall": 0.0, "f1-score": 0.0, "supports": 2}, "Further Specification": {"true-positive": 0, "false-positive": 0, "true-negative": 0, "false-negative": 0, "precision": 0.0, "recall": 0.0, "f1-score": 0.0, "supports": 0}, "XOR Gateway": {"true-positive": 0, "false-positive": 0, "true-negative": 0, "false-negative": 0, "precision": 0.0, "recall": 0.0, "f1-score": 0.0, "supports": 0}, "AND Gateway": {"true-positive": 0, "false-positive": 0, "true-negative": 0, "false-negative": 0, "precision": 0.0, "recall": 0.0, "f1-score": 0.0, "supports": 0}, "Condition Specification": {"true-positive": 0, "false-positive": 0, "true-negative": 0, "false-negative": 0, "precision": 0.0, "recall": 0.0, "f1-score": 0.0, "supports": 0}}, "doc-10.10": {"Activity": {"true-positive": 4, "false-positive": 6, "true-negative": 0, "false-negative": 6, "precision": 0.4, "recall": 0.4, "f1-score": 0.4000000000000001, "supports": 10}, "Activity Data": {"true-positive": 1, "false-positive": 10, "true-negative": 0, "false-negative": 8, "precision": 0.09090909090909091, "recall": 0.1111111111111111, "f1-score": 0.09999999999999999, "supports": 9}, "Actor": {"true-positive": 0, "false-positive": 0, "true-negative": 0, "false-negative": 15, "precision": 0.0, "recall": 0.0, "f1-score": 0.0, "supports": 15}, "Further Specification": {"true-positive": 0, "false-positive": 0, "true-negative": 0, "false-negative": 1, "precision": 0.0, "recall": 0.0, "f1-score": 0.0, "supports": 1}, "XOR Gateway": {"true-positive": 0, "false-positive": 0, "true-negative": 0, "false-negative": 2, "precision": 0.0, "recall": 0.0, "f1-score": 0.0, "supports": 2}, "AND Gateway": {"true-positive": 0, "false-positive": 0, "true-negative": 0, "false-negative": 0, "precision": 0.0, "recall": 0.0, "f1-score": 0.0, "supports": 0}, "Condition Specification": {"true-positive": 0, "false-positive": 0, "true-negative": 0, "false-negative": 0, "precision": 0.0, "recall": 0.0, "f1-score": 0.0, "supports": 0}}, "doc-9.3": {"Activity": {"true-positive": 3, "false-positive": 6, "true-negative": 0, "false-negative": 6, "precision": 0.3333333333333333, "recall": 0.3333333333333333, "f1-score": 0.3333333333333333, "supports": 9}, "Activity Data": {"true-positive": 1, "false-positive": 9, "true-negative": 0, "false-negative": 6, "precision": 0.1, "recall": 0.14285714285714285, "f1-score": 0.11764705882352941, "supports": 7}, "Actor": {"true-positive": 0, "false-positive": 0, "true-negative": 0, "false-negative": 6, "precision": 0.0, "recall": 0.0, "f1-score": 0.0, "supports": 6}, "Further Specification": {"true-positive": 0, "false-positive": 0, "true-negative": 0, "false-negative": 1, "precision": 0.0, "recall": 0.0, "f1-score": 0.0, "supports": 1}, "XOR Gateway": {"true-positive": 0, "false-positive": 0, "true-negative": 0, "false-negative": 0, "precision": 0.0, "recall": 0.0, "f1-score": 0.0, "supports": 0}, "AND Gateway": {"true-positive": 0, "false-positive": 0, "true-negative": 0, "false-negative": 0, "precision": 0.0, "recall": 0.0, "f1-score": 0.0, "supports": 0}, "Condition Specification": {"true-positive": 0, "false-positive": 0, "true-negative": 0, "false-negative": 0, "precision": 0.0, "recall": 0.0, "f1-score": 0.0, "supports": 0}}, "doc-6.4": {"Activity": {"true-positive": 4, "false-positive": 8, "true-negative": 0, "false-negative": 9, "precision": 0.3333333333333333, "recall": 0.3076923076923077, "f1-score": 0.32, "supports": 13}, "Activity Data": {"true-positive": 4, "false-positive": 10, "true-negative": 0, "false-negative": 6, "precision": 0.2857142857142857, "recall": 0.4, "f1-score": 0.3333333333333333, "supports": 10}, "Actor": {"true-positive": 0, "false-positive": 0, "true-negative": 0, "false-negative": 10, "precision": 0.0, "recall": 0.0, "f1-score": 0.0, "supports": 10}, "Further Specification": {"true-positive": 0, "false-positive": 0, "true-negative": 0, "false-negative": 0, "precision": 0.0, "recall": 0.0, "f1-score": 0.0, "supports": 0}, "XOR Gateway": {"true-positive": 0, "false-positive": 0, "true-negative": 0, "false-negative": 7, "precision": 0.0, "recall": 0.0, "f1-score": 0.0, "supports": 7}, "AND Gateway": {"true-positive": 0, "false-positive": 0, "true-negative": 0, "false-negative": 0, "precision": 0.0, "recall": 0.0, "f1-score": 0.0, "supports": 0}, "Condition Specification": {"true-positive": 0, "false-positive": 0, "true-negative": 0, "false-negative": 4, "precision": 0.0, "recall": 0.0, "f1-score": 0.0, "supports": 4}}, "doc-3.2": {"Activity": {"true-positive": 0, "false-positive": 9, "true-negative": 0, "false-negative": 6, "precision": 0.0, "recall": 0.0, "f1-score": 0.0, "supports": 6}, "Activity Data": {"true-positive": 2, "false-positive": 9, "true-negative": 0, "false-negative": 4, "precision": 0.18181818181818182, "recall": 0.3333333333333333, "f1-score": 0.23529411764705885, "supports": 6}, "Actor": {"true-positive": 0, "false-positive": 0, "true-negative": 0, "false-negative": 2, "precision": 0.0, "recall": 0.0, "f1-score": 0.0, "supports": 2}, "Further Specification": {"true-positive": 0, "false-positive": 0, "true-negative": 0, "false-negative": 1, "precision": 0.0, "recall": 0.0, "f1-score": 0.0, "supports": 1}, "XOR Gateway": {"true-positive": 0, "false-positive": 0, "true-negative": 0, "false-negative": 2, "precision": 0.0, "recall": 0.0, "f1-score": 0.0, "supports": 2}, "AND Gateway": {"true-positive": 0, "false-positive": 0, "true-negative": 0, "false-negative": 1, "precision": 0.0, "recall": 0.0, "f1-score": 0.0, "supports": 1}, "Condition Specification": {"true-positive": 0, "false-positive": 0, "true-negative": 0, "false-negative": 1, "precision": 0.0, "recall": 0.0, "f1-score": 0.0, "supports": 1}}, "doc-6.2": {"Activity": {"true-positive": 0, "false-positive": 0, "true-negative": 0, "false-negative": 5, "precision": 0.0, "recall": 0.0, "f1-score": 0.0, "supports": 5}, "Activity Data": {"true-positive": 0, "false-positive": 0, "true-negative": 0, "false-negative": 5, "precision": 0.0, "recall": 0.0, "f1-score": 0.0, "supports": 5}, "Actor": {"true-positive": 0, "false-positive": 0, "true-negative": 0, "false-negative": 7, "precision": 0.0, "recall": 0.0, "f1-score": 0.0, "supports": 7}, "Further Specification": {"true-positive": 0, "false-positive": 0, "true-negative": 0, "false-negative": 1, "precision": 0.0, "recall": 0.0, "f1-score": 0.0, "supports": 1}, "XOR Gateway": {"true-positive": 0, "false-positive": 0, "true-negative": 0, "false-negative": 0, "precision": 0.0, "recall": 0.0, "f1-score": 0.0, "supports": 0}, "AND Gateway": {"true-positive": 0, "false-positive": 0, "true-negative": 0, "false-negative": 0, "precision": 0.0, "recall": 0.0, "f1-score": 0.0, "supports": 0}, "Condition Specification": {"true-positive": 0, "false-positive": 0, "true-negative": 0, "false-negative": 0, "precision": 0.0, "recall": 0.0, "f1-score": 0.0, "supports": 0}}, "doc-10.2": {"Activity": {"true-positive": 2, "false-positive": 17, "true-negative": 0, "false-negative": 16, "precision": 0.10526315789473684, "recall": 0.1111111111111111, "f1-score": 0.10810810810810811, "supports": 18}, "Activity Data": {"true-positive": 2, "false-positive": 19, "true-negative": 0, "false-negative": 15, "precision": 0.09523809523809523, "recall": 0.11764705882352941, "f1-score": 0.10526315789473684, "supports": 17}, "Actor": {"true-positive": 0, "false-positive": 0, "true-negative": 0, "false-negative": 34, "precision": 0.0, "recall": 0.0, "f1-score": 0.0, "supports": 34}, "Further Specification": {"true-positive": 0, "false-positive": 0, "true-negative": 0, "false-negative": 0, "precision": 0.0, "recall": 0.0, "f1-score": 0.0, "supports": 0}, "XOR Gateway": {"true-positive": 0, "false-positive": 0, "true-negative": 0, "false-negative": 5, "precision": 0.0, "recall": 0.0, "f1-score": 0.0, "supports": 5}, "AND Gateway": {"true-positive": 0, "false-positive": 0, "true-negative": 0, "false-negative": 0, "precision": 0.0, "recall": 0.0, "f1-score": 0.0, "supports": 0}, "Condition Specification": {"true-positive": 0, "false-positive": 0, "true-negative": 0, "false-negative": 3, "precision": 0.0, "recall": 0.0, "f1-score": 0.0, "supports": 3}}, "doc-9.4": {"Activity": {"true-positive": 2, "false-positive": 5, "true-negative": 0, "false-negative": 8, "precision": 0.2857142857142857, "recall": 0.2, "f1-score": 0.23529411764705882, "supports": 10}, "Activity Data": {"true-positive": 1, "false-positive": 6, "true-negative": 0, "false-negative": 8, "precision": 0.14285714285714285, "recall": 0.1111111111111111, "f1-score": 0.125, "supports": 9}, "Actor": {"true-positive": 0, "false-positive": 0, "true-negative": 0, "false-negative": 8, "precision": 0.0, "recall": 0.0, "f1-score": 0.0, "supports": 8}, "Further Specification": {"true-positive": 0, "false-positive": 0, "true-negative": 0, "false-negative": 0, "precision": 0.0, "recall": 0.0, "f1-score": 0.0, "supports": 0}, "XOR Gateway": {"true-positive": 0, "false-positive": 0, "true-negative": 0, "false-negative": 0, "precision": 0.0, "recall": 0.0, "f1-score": 0.0, "supports": 0}, "AND Gateway": {"true-positive": 0, "false-positive": 0, "true-negative": 0, "false-negative": 0, "precision": 0.0, "recall": 0.0, "f1-score": 0.0, "supports": 0}, "Condition Specification": {"true-positive": 0, "false-positive": 0, "true-negative": 0, "false-negative": 0, "precision": 0.0, "recall": 0.0, "f1-score": 0.0, "supports": 0}}, "doc-1.4": {"Activity": {"true-positive": 4, "false-positive": 22, "true-negative": 0, "false-negative": 7, "precision": 0.15384615384615385, "recall": 0.36363636363636365, "f1-score": 0.21621621621621623, "supports": 11}, "Activity Data": {"true-positive": 6, "false-positive": 23, "true-negative": 0, "false-negative": 4, "precision": 0.20689655172413793, "recall": 0.6, "f1-score": 0.3076923076923077, "supports": 10}, "Actor": {"true-positive": 0, "false-positive": 0, "true-negative": 0, "false-negative": 8, "precision": 0.0, "recall": 0.0, "f1-score": 0.0, "supports": 8}, "Further Specification": {"true-positive": 0, "false-positive": 0, "true-negative": 0, "false-negative": 2, "precision": 0.0, "recall": 0.0, "f1-score": 0.0, "supports": 2}, "XOR Gateway": {"true-positive": 0, "false-positive": 0, "true-negative": 0, "false-negative": 0, "precision": 0.0, "recall": 0.0, "f1-score": 0.0, "supports": 0}, "AND Gateway": {"true-positive": 0, "false-positive": 0, "true-negative": 0, "false-negative": 1, "precision": 0.0, "recall": 0.0, "f1-score": 0.0, "supports": 1}, "Condition Specification": {"true-positive": 0, "false-positive": 0, "true-negative": 0, "false-negative": 0, "precision": 0.0, "recall": 0.0, "f1-score": 0.0, "supports": 0}}, "supports": 1660, "micro-statistics": {"overall-statistics": {"precision": 0.18729372937293728, "recall": 0.13674698795180723, "f1-score": 0.1580779944289694, "supports": {"supports": 1660}}, "per-class-statistics": {"Activity": {"precision": 0.12886597938144329, "recall": 0.1497005988023952, "f1-score": 0.13850415512465375, "supports": 501}, "Activity Data": {"precision": 0.24126984126984127, "recall": 0.3370288248337029, "f1-score": 0.28122109158186864, "supports": 451}, "Actor": {"precision": 0.0, "recall": 0.0, "f1-score": 0.0, "supports": 439}, "Further Specification": {"precision": 0.0, "recall": 0.0, "f1-score": 0.0, "supports": 64}, "XOR Gateway": {"precision": 0.0, "recall": 0.0, "f1-score": 0.0, "supports": 117}, "AND Gateway": {"precision": 0.0, "recall": 0.0, "f1-score": 0.0, "supports": 8}, "Condition Specification": {"precision": 0.0, "recall": 0.0, "f1-score": 0.0, "supports": 80}}}, "macro-statistics": {"overall-statistics": {"precision": 0.059560968846832374, "recall": 0.07710963062709118, "f1-score": 0.06436534823434281, "supports": {"supports": 1660}}, "per-class-statistics": {"Activity": {"precision": 0.1488805856853229, "recall": 0.16861877551718113, "f1-score": 0.15397818092879634, "supports": 501}, "Activity Data": {"precision": 0.2680461962425037, "recall": 0.3711486388724572, "f1-score": 0.29657925671160335, "supports": 451}, "Actor": {"precision": 0.0, "recall": 0.0, "f1-score": 0.0, "supports": 439}, "Further Specification": {"precision": 0.0, "recall": 0.0, "f1-score": 0.0, "supports": 64}, "XOR Gateway": {"precision": 0.0, "recall": 0.0, "f1-score": 0.0, "supports": 117}, "AND Gateway": {"precision": 0.0, "recall": 0.0, "f1-score": 0.0, "supports": 8}, "Condition Specification": {"precision": 0.0, "recall": 0.0, "f1-score": 0.0, "supports": 80}}}, "average-statistics": {"overall-statistics": {"precision": 0.10827684637077523, "recall": 0.13674698795180723, "f1-score": 0.11208062623756297, "supports": {"supports": 1660}}, "per-class-statistics": {"Activity": {"precision": 0.12503478078897695, "recall": 0.1497005988023952, "f1-score": 0.132338163981676, "supports": 501}, "Activity Data": {"precision": 0.25963889090955516, "recall": 0.3370288248337029, "f1-score": 0.26552642882380234, "supports": 451}, "Actor": {"precision": 0.0, "recall": 0.0, "f1-score": 0.0, "supports": 439}, "Further Specification": {"precision": 0.0, "recall": 0.0, "f1-score": 0.0, "supports": 64}, "XOR Gateway": {"precision": 0.0, "recall": 0.0, "f1-score": 0.0, "supports": 117}, "AND Gateway": {"precision": 0.0, "recall": 0.0, "f1-score": 0.0, "supports": 8}, "Condition Specification": {"precision": 0.0, "recall": 0.0, "f1-score": 0.0, "supports": 80}}}}